polyinfer/__init__.py
polyinfer/__main__.py
polyinfer/_logging.py
polyinfer/cli.py
polyinfer/compare.py
polyinfer/config.py
polyinfer/discovery.py
polyinfer/mlir.py
polyinfer/model.py
polyinfer/nvidia_setup.py
polyinfer/quantization.py
polyinfer/backends/__init__.py
polyinfer/backends/_autoload.py
polyinfer/backends/base.py
polyinfer/backends/registry.py
polyinfer/backends/iree/__init__.py
polyinfer/backends/iree/backend.py
polyinfer/backends/onnxruntime/__init__.py
polyinfer/backends/onnxruntime/backend.py
polyinfer/backends/openvino/__init__.py
polyinfer/backends/openvino/backend.py
polyinfer/backends/tensorrt/__init__.py
polyinfer/backends/tensorrt/backend.py
polyinfer-0.2.0.dist-info/METADATA
polyinfer-0.2.0.dist-info/WHEEL
polyinfer-0.2.0.dist-info/entry_points.txt
polyinfer-0.2.0.dist-info/licenses/LICENSE
polyinfer-0.2.0.dist-info/RECORD
