Metadata-Version: 2.4
Name: polyinfer
Version: 0.2.0
Summary: Unified ML inference across multiple backends: ONNX Runtime, OpenVINO, TensorRT, IREE
Project-URL: Homepage, https://github.com/athrva98/polyinfer
Project-URL: Documentation, https://github.com/athrva98/polyinfer#readme
Project-URL: Repository, https://github.com/athrva98/polyinfer
Project-URL: Issues, https://github.com/athrva98/polyinfer/issues
Author-email: Athrva Pandhare <athrva98@gmail.com>
License-Expression: Apache-2.0
License-File: LICENSE
Keywords: amd,deep-learning,gpu,inference,intel,iree,machine-learning,mlir,nvidia,onnx,onnxruntime,openvino,tensorrt,vulkan
Classifier: Development Status :: 3 - Alpha
Classifier: Intended Audience :: Developers
Classifier: Intended Audience :: Science/Research
Classifier: License :: OSI Approved :: MIT License
Classifier: Programming Language :: Python :: 3
Classifier: Programming Language :: Python :: 3.10
Classifier: Programming Language :: Python :: 3.11
Classifier: Programming Language :: Python :: 3.12
Classifier: Topic :: Scientific/Engineering :: Artificial Intelligence
Requires-Python: >=3.10
Requires-Dist: numpy>=1.24
Requires-Dist: onnx>=1.14
Provides-Extra: all
Requires-Dist: iree-base-compiler>=3.0; extra == 'all'
Requires-Dist: iree-base-runtime>=3.0; extra == 'all'
Requires-Dist: onnxruntime-gpu>=1.17; extra == 'all'
Requires-Dist: onnxruntime>=1.17; extra == 'all'
Requires-Dist: openvino>=2024.0; extra == 'all'
Requires-Dist: torch>=2.0; extra == 'all'
Requires-Dist: torchvision>=0.15; extra == 'all'
Provides-Extra: amd
Requires-Dist: iree-base-compiler>=3.0; extra == 'amd'
Requires-Dist: iree-base-runtime>=3.0; extra == 'amd'
Requires-Dist: onnxruntime-directml>=1.17; extra == 'amd'
Requires-Dist: torch>=2.0; extra == 'amd'
Requires-Dist: torchvision>=0.15; extra == 'amd'
Provides-Extra: cpu
Requires-Dist: iree-base-compiler>=3.0; extra == 'cpu'
Requires-Dist: iree-base-runtime>=3.0; extra == 'cpu'
Requires-Dist: onnxruntime>=1.17; extra == 'cpu'
Requires-Dist: openvino>=2024.0; extra == 'cpu'
Requires-Dist: torch>=2.0; extra == 'cpu'
Requires-Dist: torchvision>=0.15; extra == 'cpu'
Provides-Extra: dev
Requires-Dist: mypy>=1.0; extra == 'dev'
Requires-Dist: onnxruntime>=1.17; extra == 'dev'
Requires-Dist: pytest-benchmark>=4.0; extra == 'dev'
Requires-Dist: pytest>=7.0; extra == 'dev'
Requires-Dist: ruff>=0.1; extra == 'dev'
Provides-Extra: examples
Requires-Dist: diffusers>=0.25; extra == 'examples'
Requires-Dist: onnxscript>=0.1; extra == 'examples'
Requires-Dist: opencv-python>=4.8; extra == 'examples'
Requires-Dist: optimum[onnxruntime]>=1.16; extra == 'examples'
Requires-Dist: pillow>=9.0; extra == 'examples'
Requires-Dist: segment-anything; extra == 'examples'
Requires-Dist: transformers>=4.30; extra == 'examples'
Requires-Dist: ultralytics>=8.0; extra == 'examples'
Provides-Extra: intel
Requires-Dist: iree-base-compiler>=3.0; extra == 'intel'
Requires-Dist: iree-base-runtime>=3.0; extra == 'intel'
Requires-Dist: openvino>=2024.0; extra == 'intel'
Requires-Dist: torch>=2.0; extra == 'intel'
Requires-Dist: torchvision>=0.15; extra == 'intel'
Provides-Extra: iree
Requires-Dist: iree-base-compiler[onnx]>=3.0; extra == 'iree'
Requires-Dist: iree-base-runtime>=3.0; extra == 'iree'
Provides-Extra: nvidia
Requires-Dist: iree-base-compiler>=3.0; extra == 'nvidia'
Requires-Dist: iree-base-runtime>=3.0; extra == 'nvidia'
Requires-Dist: onnxruntime-gpu>=1.17; extra == 'nvidia'
Requires-Dist: tensorrt-cu12-libs>=10.0; extra == 'nvidia'
Requires-Dist: torch>=2.0; extra == 'nvidia'
Requires-Dist: torchvision>=0.15; extra == 'nvidia'
Provides-Extra: onnxruntime
Requires-Dist: onnxruntime>=1.17; extra == 'onnxruntime'
Provides-Extra: onnxruntime-directml
Requires-Dist: onnxruntime-directml>=1.17; extra == 'onnxruntime-directml'
Provides-Extra: onnxruntime-gpu
Requires-Dist: onnxruntime-gpu>=1.17; extra == 'onnxruntime-gpu'
Provides-Extra: openvino
Requires-Dist: openvino>=2024.0; extra == 'openvino'
Provides-Extra: tensorrt
Requires-Dist: cuda-python>=12.0; extra == 'tensorrt'
Requires-Dist: tensorrt-cu12>=10.0; extra == 'tensorrt'
Provides-Extra: tier1
Requires-Dist: onnxruntime>=1.17; extra == 'tier1'
Requires-Dist: openvino>=2024.0; extra == 'tier1'
Provides-Extra: tier2
Requires-Dist: onnxruntime-gpu>=1.17; extra == 'tier2'
Provides-Extra: vulkan
Requires-Dist: iree-base-compiler[onnx]>=3.0; extra == 'vulkan'
Requires-Dist: iree-base-runtime>=3.0; extra == 'vulkan'
Requires-Dist: torch>=2.0; extra == 'vulkan'
Requires-Dist: torchvision>=0.15; extra == 'vulkan'
